pysimultan_freecad/__about__.py
pysimultan_freecad/__init__.py
pysimultan_freecad/config.py
pysimultan_freecad/freecad/__init__.py
pysimultan_freecad/freecad/geometry.py
pysimultan_freecad/freecad/geometry_utils.py
pysimultan_freecad/freecad/logger.py
pysimultan_freecad/freecad/tools.py
pysimultan_freecad/freecad/fc_geometry/__init__.py
pysimultan_freecad/freecad/fc_geometry/assembly.py
pysimultan_freecad/freecad/fc_geometry/base_fc_geometry.py
pysimultan_freecad/freecad/fc_geometry/edge.py
pysimultan_freecad/freecad/fc_geometry/face.py
pysimultan_freecad/freecad/fc_geometry/fc_geometry.py
pysimultan_freecad/freecad/fc_geometry/feature.py
pysimultan_freecad/freecad/fc_geometry/solid.py
pysimultan_freecad/freecad/fc_geometry/vertex.py
pysimultan_freecad/freecad/fc_geometry/wire.py
pysimultan_freecad/freecad/utils/__init__.py
pysimultan_freecad/freecad/utils/geometry.py
pysimultan_freecad/freecad/utils/im_export.py
pysimultan_freecad/freecad/utils/obb.py
pysimultan_freecad/freecad/utils/timeout.py
pysimultan_freecad/freecad/utils/tools.py
pysimultan_freecad/mapping/__init__.py
pysimultan_freecad/mapping/contents.py
pysimultan_freecad/mapping/mapper.py
pysimultan_freecad/mapping/maps.py
pysimultan_freecad/mapping/method_mapper.py
pysimultan_freecad/mapping/view_manager.py
pysimultan_freecad-0.0.5.dist-info/METADATA
pysimultan_freecad-0.0.5.dist-info/WHEEL
pysimultan_freecad-0.0.5.dist-info/licenses/LICENSE.txt
pysimultan_freecad-0.0.5.dist-info/RECORD
